TradingLib/__init__.py
TradingLib/upload_s3.py
TradingLib-0.0.1.dist-info/METADATA
TradingLib-0.0.1.dist-info/WHEEL
TradingLib-0.0.1.dist-info/top_level.txt
TradingLib-0.0.1.dist-info/RECORD
