Metadata-Version: 2.1
Name: TradingLib
Version: 0.0.1
Summary: Библиотека для биржевой торговли MOEX
Home-page: 
Author: ryakub
Author-email: yakubovsky.rom@yandex.ru
Project-URL: GitHub, https://github.com/ryakub01
Keywords: ryakub
Classifier: Programming Language :: Python :: 3.9
Classifier: License :: OSI Approved :: MIT License
Classifier: Operating System :: OS Independent
Requires-Python: >=3.6
Requires-Dist: requests>=2.32.5
Requires-Dist: pyarrow==21.0.0
Requires-Dist: boto3==1.40.22
Requires-Dist: pandas==2.3.2
